fakebotdetector
